CHANGELOG.txt
LICENSE.txt
MANIFEST.in
requirements.txt
setup.py
chrislys/__init__.py
chrislys/functions.py
chrislys.egg-info/PKG-INFO
chrislys.egg-info/SOURCES.txt
chrislys.egg-info/dependency_links.txt
chrislys.egg-info/top_level.txt
twine/__init__.py
twine/__main__.py
twine/auth.py
twine/cli.py
twine/exceptions.py
twine/package.py
twine/repository.py
twine/settings.py
twine/utils.py
twine/wheel.py
twine/wininst.py
twine/commands/__init__.py
twine/commands/check.py
twine/commands/register.py
twine/commands/upload.py