Metadata-Version: 2.1
Name: chrislys
Version: 0.0.1
Summary: test qualys library
Author: Chris Nam
License: MIT
License-File: LICENSE.txt
